carwatch/__init__.py
carwatch/example_data.py
carwatch/examples/__init__.py
carwatch/examples/generate_labels.py
carwatch/examples/generate_qr_code.py
carwatch/labels/__init__.py
carwatch/labels/barcode_template.tex
carwatch/labels/label_generator.py
carwatch/labels/print_layout.py
carwatch/logs/__init__.py
carwatch/logs/_participant_logs.py
carwatch/logs/_study_logs.py
carwatch/logs/_utils.py
carwatch/qr_codes/__init__.py
carwatch/qr_codes/study_qr_generator.py
carwatch/scripts/__init__.py
carwatch/scripts/prepare_study.py
carwatch/utils/__init__.py
carwatch/utils/_datatype_validation_helper.py
carwatch/utils/_types.py
carwatch/utils/click_helper.py
carwatch/utils/exceptions.py
carwatch/utils/study.py
carwatch/utils/utils.py
carwatch-0.3.1.dist-info/LICENSE
carwatch-0.3.1.dist-info/METADATA
carwatch-0.3.1.dist-info/WHEEL
carwatch-0.3.1.dist-info/entry_points.txt
carwatch-0.3.1.dist-info/RECORD
