Metadata-Version: 2.1
Name: carwatch
Version: 0.3.1
Summary: A Python package for the CARWatch framework to improve cortisol awakening response sampling.
Home-page: https://github.com/mad-lab-fau/carwatch
License: MIT
Author: Annika Muecke
Author-email: annika.muecke@fau.de
Requires-Python: >=3.8,<3.11
Classifier: License :: OSI Approved :: MIT License
Classifier: Programming Language :: Python :: 3
Classifier: Programming Language :: Python :: 3.8
Classifier: Programming Language :: Python :: 3.9
Classifier: Programming Language :: Python :: 3.10
Provides-Extra: plotting
Requires-Dist: CairoSVG (>=2.5.2,<3.0.0)
Requires-Dist: click (>=8.1.3,<9.0.0)
Requires-Dist: fau_colors (>=1.6.0,<2.0.0) ; extra == "plotting"
Requires-Dist: ipympl (>=0.9,<0.10) ; extra == "plotting"
Requires-Dist: ipywidgets (>=8,<9) ; extra == "plotting"
Requires-Dist: jupyterlab (>=3.4.5,<4.0.0)
Requires-Dist: matplotlib (>=3.5.0,<4.0.0) ; extra == "plotting"
Requires-Dist: pandas (>=1.5.0,<2.0.0)
Requires-Dist: python-barcode (>=0.14.0,<0.15.0)
Requires-Dist: qrcode (>=7.3.1,<8.0.0)
Requires-Dist: seaborn (>=0.11.2,<0.12.0) ; extra == "plotting"
Requires-Dist: trogon (>=0.4.0,<0.5.0)
Project-URL: Repository, https://github.com/mad-lab-fau/carwatch
